{
  "facebook": {
    "clientID": "process.env.FACEBOOK_APP_ID",
    "clientSecret": "process.env.FACEBOOK_APP_SECRET",
    "callbackURL": "http://localhost:1337/auth/facebook/callback"
  },
  "twitter": {
    "consumerKey": "process.env.TWITTER_APP_ID",
    "consumerSecret": "process.env.TWITTER_APP_SECRET",
    "callbackURL": "http://localhost:1337/auth/twitter/callback"
  },
  "google": {
    "clientID": "process.env.GOOGLE_APP_ID",
    "clientSecret": "process.env.GOOGLE_APP_SECRET",
    "callbackURL": "http://localhost:1337/auth/google/callback"
  },
  "linkedin": {
    "clientID": "process.env.LINKEDIN_APP_ID",
    "clientSecret": "process.env.LINKEDIN_APP_SECRET",
    "callbackURL": "http://localhost:1337/auth/instagram/callback"
  }
}
